pyCoastal/__init__.py
pyCoastal/config.py
pyCoastal/io.py
pyCoastal/numerics/__init__.py
pyCoastal/numerics/boundary.py
pyCoastal/numerics/domain.py
pyCoastal/numerics/grid.py
pyCoastal/numerics/operators.py
pyCoastal/numerics/scheme.py
pyCoastal/numerics/solver.py
pyCoastal/numerics/time_intg.py
pyCoastal/numerics/wave2D.py
pyCoastal/physics/__init__.py
pyCoastal/physics/navier_stokes.py
pyCoastal/physics/poisson.py
pyCoastal/physics/shallow_water.py
pyCoastal/physics/turbulence.py
pyCoastal/tools/__init__.py
pyCoastal/tools/morphodynamics.py
pyCoastal/tools/sediment_transport.py
pyCoastal/tools/structural.py
pyCoastal/tools/wave.py
pycoastal-0.1.0.dist-info/licenses/LICENSE
pycoastal-0.1.0.dist-info/METADATA
pycoastal-0.1.0.dist-info/WHEEL
pycoastal-0.1.0.dist-info/top_level.txt
pycoastal-0.1.0.dist-info/RECORD
