Metadata-Version: 2.4
Name: pyCoastal
Version: 0.1.0
Summary: A Python toolbox for coastal engineering
Home-page: https://github.com/yourusername/pyCoastal
Author: stebiondi
Author-email: Stefano Biondi <stefano@example.com>
License: MIT
Classifier: Programming Language :: Python :: 3
Classifier: License :: OSI Approved :: MIT License
Classifier: Operating System :: OS Independent
Requires-Python: >=3.7
License-File: LICENSE
Dynamic: author
Dynamic: home-page
Dynamic: license-file
Dynamic: requires-python
